ipld_dag_pb/__init__.py
ipld_dag_pb/dag-pb.proto
ipld_dag_pb/decode.py
ipld_dag_pb/encode.py
ipld_dag_pb/node.py
ipld_dag_pb/util.py
ipld_dag_pb-0.0.1.dist-info/METADATA
ipld_dag_pb-0.0.1.dist-info/WHEEL
ipld_dag_pb-0.0.1.dist-info/licenses/LICENSE.md
ipld_dag_pb-0.0.1.dist-info/RECORD
