Metadata-Version: 2.4
Name: ipld_dag_pb
Version: 0.0.1
Summary: An implementation of the DAG-PB spec for Python.
Project-URL: Homepage, https://github.com/storacha/py-ipld-dag-pb
Project-URL: Issues, https://github.com/storacha/py-ipld-dag-pb/issues
Author-email: Alan Shaw <alan@storacha.network>
License-Expression: Apache-2.0 OR MIT
License-File: LICENSE.md
Classifier: Operating System :: OS Independent
Classifier: Programming Language :: Python :: 3
Requires-Python: >=3.9
